django_linkcheck-2.4.0.dist-info/licenses/LICENSE
linkcheck/__init__.py
linkcheck/admin_blocks.py
linkcheck/apps.py
linkcheck/build_meta.py
linkcheck/cron.py
linkcheck/dashboard.py
linkcheck/filebrowser.py
linkcheck/linkcheck_settings.py
linkcheck/listeners.py
linkcheck/models.py
linkcheck/urls.py
linkcheck/utils.py
linkcheck/views.py
linkcheck/locale/de/LC_MESSAGES/django.mo
linkcheck/locale/fr/LC_MESSAGES/django.mo
linkcheck/management/__init__.py
linkcheck/management/commands/__init__.py
linkcheck/management/commands/checkexternal.py
linkcheck/management/commands/checkinternal.py
linkcheck/management/commands/checklinks.py
linkcheck/management/commands/findlinks.py
linkcheck/management/commands/linkcheck_suggest_config.py
linkcheck/management/commands/unignore_links.py
linkcheck/migrations/0001_initial.py
linkcheck/migrations/0002_url_redirect_to.py
linkcheck/migrations/0003_redirect_to_as_textfield.py
linkcheck/migrations/0004_remove_url_still_exists.py
linkcheck/migrations/0005_default_big_auto_field.py
linkcheck/migrations/0006_url_add_status_code.py
linkcheck/migrations/0007_url_add_redirect_status_code.py
linkcheck/migrations/0008_url_add_anchor_status.py
linkcheck/migrations/0009_url_add_ssl_status.py
linkcheck/migrations/0010_url_add_error_message.py
linkcheck/migrations/0011_link_add_content_object_index.py
linkcheck/migrations/__init__.py
linkcheck/templates/linkcheck/base_linkcheck.html
linkcheck/templates/linkcheck/paginator.html
linkcheck/templates/linkcheck/report.html
linkcheck/templatetags/__init__.py
linkcheck/templatetags/linkcheck_model_tags.py
linkcheck/tests/__init__.py
linkcheck/tests/test_linkcheck.py
linkcheck/tests/urls.py
linkcheck/tests/media/found
linkcheck/tests/sampleapp/__init__.py
linkcheck/tests/sampleapp/linklists.py
linkcheck/tests/sampleapp/models.py
linkcheck/tests/sampleapp/views.py
django_linkcheck-2.4.0.dist-info/METADATA
django_linkcheck-2.4.0.dist-info/WHEEL
django_linkcheck-2.4.0.dist-info/top_level.txt
django_linkcheck-2.4.0.dist-info/RECORD
