Metadata-Version: 2.4
Name: django-linkcheck
Version: 2.4.0
Summary: A Django app that will analyze and report on links in any model that you register with it.
Author-email: Andy Baker <andy@andybak.net>, Fruits Chen <fruitschen@gmail.com>, Tim Graves <gravesit@gmail.com>, Jannis Leidel <jannis@leidel.info>, Claude Paroz <claude@2xlibre.net>, Timo Brembeck <opensource@timo.brembeck.email>
License-Expression: BSD-3-Clause
Project-URL: Homepage, https://github.com/DjangoAdminHackers/django-linkcheck
Project-URL: Issues, https://github.com/DjangoAdminHackers/django-linkcheck/issues
Project-URL: Changelog, https://github.com/DjangoAdminHackers/django-linkcheck/blob/master/CHANGELOG
Classifier: Development Status :: 5 - Production/Stable
Classifier: Environment :: Web Environment
Classifier: Intended Audience :: Developers
Classifier: Operating System :: OS Independent
Classifier: Programming Language :: Python
Classifier: Programming Language :: Python :: 3
Classifier: Programming Language :: Python :: 3 :: Only
Classifier: Programming Language :: Python :: 3.9
Classifier: Programming Language :: Python :: 3.10
Classifier: Programming Language :: Python :: 3.11
Classifier: Programming Language :: Python :: 3.12
Classifier: Programming Language :: Python :: 3.13
Classifier: Framework :: Django
Classifier: Framework :: Django :: 4.2
Classifier: Framework :: Django :: 5.0
Classifier: Framework :: Django :: 5.1
Classifier: Framework :: Django :: 5.2
Requires-Python: >=3.9
License-File: LICENSE
Requires-Dist: django>=4.2
Requires-Dist: requests
Provides-Extra: dev
Requires-Dist: build; extra == "dev"
Requires-Dist: flake8; extra == "dev"
Requires-Dist: isort; extra == "dev"
Requires-Dist: pre-commit; extra == "dev"
Requires-Dist: requests_mock; extra == "dev"
Dynamic: license-file
